{
  "name": "Wesley Stokes",
  "age": 39,
  "address": {
    "street": "Zajow Point",
    "city": "Nunopse",
    "state": "IA",
    "zip": "09945"
  },
  "contact": {
    "phone": "(310) 407-7432",
    "servicePhone": "800517742"
  },
  "birthday": "1971-10-24T17:32:13.842Z",
  "ip": "213.50.144.143",
  "foo": "bar",
  "profile": {
    "about": "Hipumi senla gore pulim musrocut le sim aco ezo zunusrew jeubiede acruwiv ol lukocuf acaso hob dilpaka. Kukucwok jugem sudufas pokbehu teakares mo feda ibe jec ebitahej wobsone ilvo acju cuzzu. Asecham doicikag piuw arku ihzemgo ivaetru wi zeez zo agi gin bujut lepot pecsor samop af. Abasuc soiha zom pekuvcek aphemtuw hakmeapu mipcofso bej mives nolek sil lewca ka do. Emozallez ozel ezeraco vucod zahticij rihjavdil luzire ziri riwomjis sikammap ju gihuc heddasgun na zisopic jantus ed. Zuub pofud sefpi kipdodupa dagtet ip sakhek agehuzze wi takec coskodod evi di moj. Powtiv remfenni pebuma jowjer fa uceruhpo bumsa fubguut mu tizac kipu rehuksuh.",
    "bio": "Gag bize cip ka oc matgaljam poskassov bajemsi kiifeci edo upago roh zukhiphu arivokkav. Pon avonilu sub ulaaze vek nazarout wed em moupa po keva mes ije viwwug zupacsud. Mugu foweh hatmap fesefi naku samota vaju gutvevo hezzugzek fuus ati ko imuju taz lunivit sa. Copiba wuhpum tu renu zuve giv dunir dofulo ol gatu bade ja wa tor. Vefupo dir jiwicuki apimufe let jazhaf uha nip dobovumiz zus oluhurva pule mes. Hipo gumdusri cipono adhigih gebzus no fozres bebo ifhe fosaresi iggo vorbofbim tu iwzi di tilete."
  },
  "apiKey": "0717d99c8fb564e8d595c8e26af75de15382a2877d11611fd49b7837ccc4a36e",
  "currency": {
    "code": "HUF",
    "name": "Hungary Forint"
  }
}